glaip_sdk/__init__.py
glaip_sdk/_version.py
glaip_sdk/branding.py
glaip_sdk/exceptions.py
glaip_sdk/icons.py
glaip_sdk/ptc.py
glaip_sdk/rich_components.py
glaip_sdk/agents/__init__.py
glaip_sdk/agents/base.py
glaip_sdk/agents/component.py
glaip_sdk/cli/__init__.py
glaip_sdk/cli/account_store.py
glaip_sdk/cli/agent_config.py
glaip_sdk/cli/auth.py
glaip_sdk/cli/config.py
glaip_sdk/cli/constants.py
glaip_sdk/cli/context.py
glaip_sdk/cli/display.py
glaip_sdk/cli/entrypoint.py
glaip_sdk/cli/hints.py
glaip_sdk/cli/io.py
glaip_sdk/cli/main.py
glaip_sdk/cli/masking.py
glaip_sdk/cli/mcp_validators.py
glaip_sdk/cli/pager.py
glaip_sdk/cli/resolution.py
glaip_sdk/cli/rich_helpers.py
glaip_sdk/cli/tui_settings.py
glaip_sdk/cli/update_notifier.py
glaip_sdk/cli/validators.py
glaip_sdk/cli/commands/__init__.py
glaip_sdk/cli/commands/accounts.py
glaip_sdk/cli/commands/common_config.py
glaip_sdk/cli/commands/configure.py
glaip_sdk/cli/commands/models.py
glaip_sdk/cli/commands/transcripts_original.py
glaip_sdk/cli/commands/update.py
glaip_sdk/cli/commands/agents/__init__.py
glaip_sdk/cli/commands/agents/_common.py
glaip_sdk/cli/commands/agents/create.py
glaip_sdk/cli/commands/agents/delete.py
glaip_sdk/cli/commands/agents/get.py
glaip_sdk/cli/commands/agents/list.py
glaip_sdk/cli/commands/agents/run.py
glaip_sdk/cli/commands/agents/sync_langflow.py
glaip_sdk/cli/commands/agents/update.py
glaip_sdk/cli/commands/mcps/__init__.py
glaip_sdk/cli/commands/mcps/_common.py
glaip_sdk/cli/commands/mcps/connect.py
glaip_sdk/cli/commands/mcps/create.py
glaip_sdk/cli/commands/mcps/delete.py
glaip_sdk/cli/commands/mcps/get.py
glaip_sdk/cli/commands/mcps/list.py
glaip_sdk/cli/commands/mcps/tools.py
glaip_sdk/cli/commands/mcps/update.py
glaip_sdk/cli/commands/shared/__init__.py
glaip_sdk/cli/commands/shared/formatters.py
glaip_sdk/cli/commands/tools/__init__.py
glaip_sdk/cli/commands/tools/_common.py
glaip_sdk/cli/commands/tools/create.py
glaip_sdk/cli/commands/tools/delete.py
glaip_sdk-0.7.26.dist-info/METADATA
glaip_sdk-0.7.26.dist-info/WHEEL
glaip_sdk-0.7.26.dist-info/entry_points.txt
glaip_sdk-0.7.26.dist-info/top_level.txt
glaip_sdk-0.7.26.dist-info/RECORD
