Metadata-Version: 2.4
Name: glaip-sdk
Version: 0.7.26
Summary: Python SDK and CLI for GL AIP (GDP Labs AI Agent Package) - Build, run, and manage AI agents
Author-email: Raymond Christopher <raymond.christopher@gdplabs.id>
License: MIT
Requires-Python: <3.13,>=3.11
Requires-Dist: httpx>=0.28.1
Requires-Dist: pydantic>=2.0.0
Requires-Dist: pyyaml>=6.0.0
Requires-Dist: python-dotenv<2.0.0,>=1.1.1
Requires-Dist: readchar<5.0.0,>=4.2.1
Requires-Dist: questionary<3.0.0,>=2.1.0
Requires-Dist: click<8.3.0,>=8.2.0
Requires-Dist: rich>=13.0.0
Requires-Dist: packaging>=23.2
Requires-Dist: textual>=0.52.0
Requires-Dist: gllm-core-binary>=0.1.0
Requires-Dist: langchain-core>=0.3.0
Requires-Dist: gllm-tools-binary>=0.1.3
Provides-Extra: local
Requires-Dist: aip-agents-binary[local]>=0.6.4; (python_version >= "3.11" and python_version < "3.13") and extra == "local"
Provides-Extra: memory
Requires-Dist: aip-agents-binary[memory]>=0.6.4; (python_version >= "3.11" and python_version < "3.13") and extra == "memory"
Provides-Extra: privacy
Requires-Dist: aip-agents-binary[privacy]>=0.6.4; (python_version >= "3.11" and python_version < "3.13") and extra == "privacy"
Provides-Extra: guardrails
Requires-Dist: aip-agents-binary[guardrails]>=0.6.4; (python_version >= "3.11" and python_version < "3.13") and extra == "guardrails"
Provides-Extra: pipeline
Requires-Dist: gllm-pipeline-binary==0.4.23; extra == "pipeline"
Requires-Dist: gllm-inference-binary<0.6.0,>=0.5.0; extra == "pipeline"
Provides-Extra: dev
Requires-Dist: pytest>=7.0.0; extra == "dev"
Requires-Dist: pytest-cov>=4.0.0; extra == "dev"
Requires-Dist: pytest-dotenv>=0.5.2; extra == "dev"
Requires-Dist: pre-commit>=4.3.0; extra == "dev"
Requires-Dist: pytest-xdist>=3.8.0; extra == "dev"
Requires-Dist: pytest-asyncio>=0.23.6; extra == "dev"
Requires-Dist: pytest-timeout>=2.3.1; extra == "dev"
Requires-Dist: ruff>=0.14.0; extra == "dev"
